{
  "id": 631,
  "title": "Despertares nocturnos: ¿qué hacer cuando tu bebé no duerme?",
  "slug": "despertares-nocturnos-que-hacer-cuando-tu-bebe-no-duerme",
  "issue_ids": [
    314,
    279,
    352
  ],
  "content": "# Despertares nocturnos: ¿qué hacer cuando tu bebé no duerme?\n\n**Slug:** despertares-nocturnos-que-hacer-cuando-tu-bebe-no-duerme\n\n**Categoría Principal:** Sueño Infantil\n\n**Tags Asociados:** sueño, bebé, dormir, despertares tempranos, despertares falsos, despertares matutinos, sueño fragmentado, regresión del sueño, problemas de horario, asesor de sueño, consultora de sueño, consejo ineficaz, frustración\n\n\nEntendemos perfectamente la frustración que sientes cuando los despertares nocturnos de tu bebé interrumpen vuestro sueño y el vuestro propio.  Es agotador, estresante, y a veces te hace cuestionar todo lo que estás haciendo.  En este artículo, abordaremos las causas más comunes de los despertares nocturnos, especialmente los despertares tempranos y frecuentes, y te daremos algunas claves basadas en la evidencia para ayudarte a ti y a tu bebé a dormir mejor.  Exploraremos situaciones reales de otros padres y madres, como la experiencia de una mamá con un bebé de 14 meses que se despierta a las 4:30 am, gritando, desde hace un mes (Reddit).  También veremos casos de bebés con problemas de horario y despertares falsos, incluso a pesar de haber seguido un programa con un asesor de sueño (SleepyKids). Y responderemos a la pregunta que muchas familias se hacen: ¿cuándo mejoran finalmente esos molestos despertares matutinos?\n\n## ¿Por qué mi bebé se despierta tan temprano?\n\nLa respuesta a esta pregunta no es única y depende de varios factores.  A veces, se trata de un simple desajuste horario, como experimentamos en el invierno con cambios de temperatura y luz (The Baby Sleep Club). Pero en otras ocasiones, puede ser algo más complejo.  Según diferentes fuentes, las causas pueden incluir:\n\n* **Desajustes horarios:**  Un horario irregular de sueño, incluyendo siestas demasiado largas o demasiado cortas, o una ventana de sueño demasiado larga entre la última siesta y la hora de dormir, puede provocar despertares tempranos (Baby Sleep Solutions, SleepyKids).  Recuerda que un bebé que duerme mucho por el día puede despertarse más temprano por la noche.\n\n* **Sueño fragmentado:** Los despertares frecuentes pueden ser simplemente una característica normal del sueño infantil, especialmente en los primeros meses. Un estudio indica que los bebés se despiertan con más frecuencia en sus primeros meses, debido principalmente al hambre. (Baby Wellness Foundation).  La leche materna se digiere más rápido que la leche de fórmula, lo que puede significar más despertares nocturnos (Baby Wellness Foundation).  Sin embargo, después de los 6 meses, despertares muy frecuentes (cada hora o incluso cada 30 minutos) pueden ser motivo de consulta con un profesional. (EcusKids).\n\n* **Ritmo circadiano aún en desarrollo:** El reloj biológico de tu bebé todavía se está desarrollando, por lo que es posible que se despierte con el amanecer, incluso si parece tener suficiente sueño. (EcusKids).\n\n* **Ambiente de sueño inadecuado:** Asegúrate de que la habitación de tu bebé es oscura, tranquila y a una temperatura adecuada.  Esto puede marcar una gran diferencia. (SleepyKids, EcusKids)\n\n* **Terrores nocturnos:** Aunque no se relaciona directamente con los despertares tempranos, los terrores nocturnos son un trastorno común del sueño que puede causar despertares repentinos y angustiosos.  Suele ser algo que se resuelve solo antes de la adolescencia (KidsHealth), pero si tienes sospechas, consulta a un profesional.\n\n## ¿Qué puedo hacer?\n\nSi has probado diferentes estrategias sin éxito y te sientes frustrada, como la mamá de un bebé de 12 meses que describe su experiencia con una consultora del sueño (Issue ID: 279), no te desanimes.  La paciencia es clave.  \n\nComo mencionamos anteriormente, las soluciones no son mágicas y a menudo requieren tiempo para funcionar.  Sin embargo, puedes empezar por:\n\n* **Revisar los horarios de sueño y siestas:** Asegúrate de que las siestas de tu bebé son adecuadas para su edad y que la ventana de sueño antes de acostarse no es demasiado larga.\n\n* **Crear una rutina relajante para la hora de dormir:** Un ambiente tranquilo y consistente antes de acostarse puede ayudar a tu bebé a dormirse más fácilmente y a dormir más profundamente.\n\n* **Optimizar el ambiente del sueño:** Asegúrate de que el cuarto es oscuro, silencioso y a una temperatura cómoda.\n\n* **Considerar la posibilidad de una consulta profesional:** Si la situación persiste y te sientes abrumada, te recomendamos que busques ayuda profesional.  Una consultora del sueño puede ayudarte a diseñar un plan personalizado para abordar los despertares nocturnos de tu bebé.  Incluso, si ya has probado con una, existen otros métodos y profesionales que podrían ayudarte.  Te recordamos que puedes realizar una valoración gratuita en [vialacteasuenoylactancia.com](vialacteasuenoylactancia.com) para evaluar tu situación individualmente y recibir apoyo personalizado.\n\n**Recuerda:** Los despertares nocturnos son muy comunes, especialmente en los primeros meses.  Con paciencia, perseverancia y, si es necesario, con ayuda profesional, puedes mejorar la calidad del sueño de tu bebé y la tuya propia.  Si has llegado hasta aquí y aún te sientes perdida, recuerda que no estás sola.  Te invitamos a programar una valoración gratuita en [vialacteasuenoylactancia.com](vialacteasuenoylactancia.com) para obtener apoyo personalizado y un plan a tu medida.",
  "meta_description": "Entendiendo los despertares nocturnos de tu bebé y cómo ayudarles a dormir mejor. ¡Reserva tu valoración gratuita!",
  "status": "published",
  "created_at": "2025-08-09T02:07:56.581Z",
  "published_at": "2025-08-09T02:07:56.581Z",
  "category": "Sueño Infantil",
  "content_html": "\n<h1>Despertares nocturnos: ¿qué hacer cuando tu bebé no duerme?</h1>\n\n<p>Entendemos perfectamente la frustración que sientes cuando los despertares nocturnos de tu bebé interrumpen vuestro sueño y el vuestro propio.  Es agotador, estresante, y a veces te hace cuestionar todo lo que estás haciendo.  En este artículo, abordaremos las causas más comunes de los despertares nocturnos, especialmente los despertares tempranos y frecuentes, y te daremos algunas claves basadas en la evidencia para ayudarte a ti y a tu bebé a dormir mejor.  Exploraremos situaciones reales de otros padres y madres, como la experiencia de una mamá con un bebé de 14 meses que se despierta a las 4:30 am, gritando, desde hace un mes (<a href=\"https://www.reddit.com/r/toddlers/comments/18nm0q8/early_morning_help_14_month_old/?tl=es-419\" target=\"_blank\" rel=\"noopener noreferrer\" class=\"via-lactea-reference\">[5]</a>).  También veremos casos de bebés con problemas de horario y despertares falsos, incluso a pesar de haber seguido un programa con un asesor de sueño (<a href=\"https://sleepykids.es/consulta-2/\" target=\"_blank\" rel=\"noopener noreferrer\" class=\"via-lactea-reference\">[2]</a>). Y responderemos a la pregunta que muchas familias se hacen: ¿cuándo mejoran finalmente esos molestos despertares matutinos?</p>\n\n<h2>¿Por qué mi bebé se despierta tan temprano?</h2>\n\n<p>La respuesta a esta pregunta no es única y depende de varios factores.  A veces, se trata de un simple desajuste horario, como experimentamos en el invierno con cambios de temperatura y luz (<a href=\"https://thebabysleepclub.com/soluciones-efectivas-para-noches-de-invierno/\" target=\"_blank\" rel=\"noopener noreferrer\" class=\"via-lactea-reference\">[4]</a>). Pero en otras ocasiones, puede ser algo más complejo.  Según diferentes fuentes, las causas pueden incluir:</p>\n\n<ul>\n<li><strong>Desajustes horarios:</strong> Un horario irregular de sueño, incluyendo siestas demasiado largas o demasiado cortas, o una ventana de sueño demasiado larga entre la última siesta y la hora de dormir, puede provocar despertares tempranos (<a href=\"https://www.babysleepsolutions.es/despertares-tempranos-bebe/\" target=\"_blank\" rel=\"noopener noreferrer\" class=\"via-lactea-reference\">[1]</a>, <a href=\"https://sleepykids.es/consulta-2/\" target=\"_blank\" rel=\"noopener noreferrer\" class=\"via-lactea-reference\">[2]</a>). Recuerda que un bebé que duerme mucho por el día puede despertarse más temprano por la noche.</li>\n<li><strong>Sueño fragmentado:</strong> Los despertares frecuentes pueden ser simplemente una característica normal del sueño infantil, especialmente en los primeros meses. Un estudio indica que los bebés se despiertan con más frecuencia en sus primeros meses, debido principalmente al hambre. (<a href=\"https://babywellnessfoundation.org/es/segreti-nanna/capitulo-3-los-despertares-nocturnos/\" target=\"_blank\" rel=\"noopener noreferrer\" class=\"via-lactea-reference\">[9]</a>). La leche materna se digiere más rápido que la leche de fórmula, lo que puede significar más despertares nocturnos (<a href=\"https://babywellnessfoundation.org/es/segreti-nanna/capitulo-3-los-despertares-nocturnos/\" target=\"_blank\" rel=\"noopener noreferrer\" class=\"via-lactea-reference\">[9]</a>). Sin embargo, después de los 6 meses, despertares muy frecuentes (cada hora o incluso cada 30 minutos) pueden ser motivo de consulta con un profesional. (<a href=\"https://ecuskids.com/blogs/blog/los-despertares-nocturnos-son-normales\" target=\"_blank\" rel=\"noopener noreferrer\" class=\"via-lactea-reference\">[10]</a>).</li>\n<li><strong>Ritmo circadiano aún en desarrollo:</strong> El reloj biológico de tu bebé todavía se está desarrollando, por lo que es posible que se despierte con el amanecer, incluso si parece tener suficiente sueño. (<a href=\"https://ecuskids.com/blogs/blog/despertar-temprano-por-que-ocurre\" target=\"_blank\" rel=\"noopener noreferrer\" class=\"via-lactea-reference\">[7]</a>).</li>\n<li><strong>Ambiente de sueño inadecuado:</strong> Asegúrate de que la habitación de tu bebé es oscura, tranquila y a una temperatura adecuada. Esto puede marcar una gran diferencia. (<a href=\"https://sleepykids.es/consulta-2/\" target=\"_blank\" rel=\"noopener noreferrer\" class=\"via-lactea-reference\">[2]</a>, <a href=\"https://ecuskids.com/blogs/blog/despertar-temprano-por-que-ocurre\" target=\"_blank\" rel=\"noopener noreferrer\" class=\"via-lactea-reference\">[7]</a>)</li>\n<li><strong>Terrores nocturnos:</strong> Aunque no se relaciona directamente con los despertares tempranos, los terrores nocturnos son un trastorno común del sueño que puede causar despertares repentinos y angustiosos. Suele ser algo que se resuelve solo antes de la adolescencia (<a href=\"https://kidshealth.org/es/parents/terrors.html\" target=\"_blank\" rel=\"noopener noreferrer\" class=\"via-lactea-reference\">[11]</a>), pero si tienes sospechas, consulta a un profesional.</li>\n</ul>\n\n<h2>¿Qué puedo hacer?</h2>\n\n<p>Si has probado diferentes estrategias sin éxito y te sientes frustrada, como la mamá de un bebé de 12 meses que describe su experiencia con una consultora del sueño (Issue ID: 279), no te desanimes. La paciencia es clave. </p>\n\n<p>Como mencionamos anteriormente, las soluciones no son mágicas y a menudo requieren tiempo para funcionar. Sin embargo, puedes empezar por:</p>\n\n<ul>\n<li>Revisar los horarios de sueño y siestas: Asegúrate de que las siestas de tu bebé son adecuadas para su edad y que la ventana de sueño antes de acostarse no es demasiado larga.</li>\n<li>Crear una rutina relajante para la hora de dormir: Un ambiente tranquilo y consistente antes de acostarse puede ayudar a tu bebé a dormirse más fácilmente y a dormir más profundamente.</li>\n<li>Optimizar el ambiente del sueño: Asegúrate de que el cuarto es oscuro, silencioso y a una temperatura cómoda.</li>\n<li>Considerar la posibilidad de una consulta profesional: Si la situación persiste y te sientes abrumada, te recomendamos que busques ayuda profesional. Una consultora del sueño puede ayudarte a diseñar un plan personalizado para abordar los despertares nocturnos de tu bebé. Incluso, si ya has probado con una, existen otros métodos y profesionales que podrían ayudarte. Te recordamos que puedes realizar una valoración gratuita en <a href=\"vialacteasuenoylactancia.com\">vialacteasuenoylactancia.com</a> para evaluar tu situación individualmente y recibir apoyo personalizado.</li>\n</ul>\n\n<h2>Recuerda:</h2>\n\n<p>Los despertares nocturnos son muy comunes, especialmente en los primeros meses. Con paciencia, perseverancia y, si es necesario, con ayuda profesional, puedes mejorar la calidad del sueño de tu bebé y la tuya propia. Si has llegado hasta aquí y aún te sientes perdida, recuerda que no estás sola. Te invitamos a programar una valoración gratuita en <a href=\"vialacteasuenoylactancia.com\">vialacteasuenoylactancia.com</a> para obtener apoyo personalizado y un plan a tu medida.</p>\n\n\n",
  "is_featured": false,
  "tags": [
    "sueño",
    "bebé",
    "dormir",
    "despertares tempranos",
    "despertares falsos",
    "despertares matutinos",
    "sueño fragmentado",
    "regresión del sueño",
    "problemas de horario",
    "asesor de sueño",
    "consultora de sueño",
    "consejo ineficaz",
    "frustración"
  ],
  "version": 1
}